{
    "name": "",
    "homePage": "",
    "repos": {
        "https://github.com/nf-core/modules.git": {
            "modules": {
                "nf-core": {
                    "gunzip": {
                        "branch": "master",
                        "git_sha": "4e5f4687318f24ba944a13609d3ea6ebd890737d",
                        "installed_by": ["modules"]
                    },
                    "ltrfinder": {
                        "branch": "master",
                        "git_sha": "be4f907729fce59ca73b6d79545cd220544729c7",
                        "installed_by": ["modules"]
                    },
                    "ltrharvest": {
                        "branch": "master",
                        "git_sha": "78575b0b1469a12b4e5bf3427aa81011f8de4a4d",
                        "installed_by": ["modules"]
                    },
                    "ltrretriever/lai": {
                        "branch": "master",
                        "git_sha": "26c8a95ea51095e60ebe8737f081caeb0c2cb49d",
                        "installed_by": ["modules"]
                    },
                    "ltrretriever/ltrretriever": {
                        "branch": "master",
                        "git_sha": "35787cd40758c13f02565ab2a67eae94da89a374",
                        "installed_by": ["modules"]
                    }
                }
            }
        }
    }
}
